{
    "configurations": [
        {
            "name": "AVR-GCC",
            "compilerPath": "${PROGRAMFILES(x86)}/Atmel/Toolchain/avr/bin/gcc.exe",
            "intelliSenseMode": "clang-x64",
            "cStandard": "c11", 
            "includePath": [
		"${workspaceFolder}",
                "${PROGRAMFILES(x86)}/Atmel/Toolchain/avr/include/",
                "${PROGRAMFILES(x86)}/Atmel/Toolchain/avr/include/avr/",
                "${PROGRAMFILES(x86)}/Atmel/Toolchain/avr/include/compat/",
                "${PROGRAMFILES(x86)}/Atmel/Toolchain/avr/include/util/",
		"${PROGRAMFILES(x86)}/Atmel/Toolchain/lib/gcc/avr/4.5.1/include/"
            ],
            "defines": [
                "__AVR_ATmega8__",
                "F_CPU=4000000L"
            ],
            "browse": {
                "path": [
                    "${workspaceFolder}"
                ],
                "limitSymbolsToIncludedHeaders": true,
                "databaseFilename": ""
            }
        }
    ],
    "version": 4
}